pykleene/__init__.py
pykleene/_config.py
pykleene/_helpers.py
pykleene/dfa.py
pykleene/grammar.py
pykleene/lba.py
pykleene/nfa.py
pykleene/pda.py
pykleene/re.py
pykleene/symbols.py
pykleene/tm.py
pykleene/utils.py
pykleene-0.1.5.dist-info/METADATA
pykleene-0.1.5.dist-info/WHEEL
pykleene-0.1.5.dist-info/top_level.txt
pykleene-0.1.5.dist-info/RECORD
