Metadata-Version: 2.1
Name: pykleene
Version: 0.1.5
Summary: UNKNOWN
Home-page: UNKNOWN
License: UNKNOWN
Platform: UNKNOWN
Requires-Dist: graphviz==0.20.3
